LICENSE.txt
README.md
setup.py
char_counter/__init__.py
char_counter/count_chars.py
char_counter/exceptions.py
char_counter/input_validator.py
char_counter.egg-info/PKG-INFO
char_counter.egg-info/SOURCES.txt
char_counter.egg-info/dependency_links.txt
char_counter.egg-info/requires.txt
char_counter.egg-info/top_level.txt
tests/__init__.py
tests/cli_test.py
tests/test_count_unique_characters.py