Metadata-Version: 2.1
Name: char-counter
Version: 1.0.0
Summary: A command-line tool to count the characters in a text file
Home-page: https://git.foxminded.ua/foxstudent102513/task-5-create-the-python-package
Author: Uladzimir Radchanka
Author-email: Uradchanka@gmail.com
License: MIT
Classifier: Programming Language :: Python :: 3
Classifier: License :: OSI Approved :: MIT License
Classifier: Operating System :: OS Independent
License-File: LICENSE.txt
